LICENSE
MANIFEST.in
README.rst
rxncon_workbench.py
setup.py
media_cdn/hog-example/Table_S1_Hog1_acyclic_reconstruction.xls
media_cdn/hog-example-text-format/description/hog-example-text-format_quick_definition.txt
media_cdn/hog-example-text-format/graphs/hog-example-text-format_HOG Example text format_sReaGraph.xgmml
media_cdn/hog-example-text-format/rule_based/hog-example-text-format_model.bngl
media_cdn/hog-example/boolnet/hog-example_initial_vals.csv
media_cdn/hog-example/boolnet/hog-example_model.boolnet
media_cdn/hog-example/boolnet/hog-example_symbols.csv
media_cdn/hog-example/graphs/hog-example_Table_S1_Hog1_acyclic_reconstruction_reaGraph.xgmml
rxncon_workbench.egg-info/PKG-INFO
rxncon_workbench.egg-info/SOURCES.txt
rxncon_workbench.egg-info/dependency_links.txt
rxncon_workbench.egg-info/requires.txt
rxncon_workbench.egg-info/top_level.txt
src/TODO~
src/__init__.py
src/crud.md
src/db.sqlite3
src/manage.py
src/.idea/.name
src/.idea/codeStyleSettings.xml
src/.idea/misc.xml
src/.idea/modules.xml
src/.idea/rxncon_site.iml
src/.idea/vcs.xml
src/.idea/workspace.xml
src/__pycache__/__init__.cpython-35.pyc
src/boolean_model/__init__.py
src/boolean_model/admin.py
src/boolean_model/apps.py
src/boolean_model/forms.py
src/boolean_model/models.py
src/boolean_model/tests.py
src/boolean_model/urls.py
src/boolean_model/views.py
src/boolean_model/__pycache__/__init__.cpython-35.pyc
src/boolean_model/__pycache__/admin.cpython-35.pyc
src/boolean_model/__pycache__/forms.cpython-35.pyc
src/boolean_model/__pycache__/models.cpython-35.pyc
src/boolean_model/__pycache__/urls.cpython-35.pyc
src/boolean_model/__pycache__/views.cpython-35.pyc
src/boolean_model/migrations/0001_initial.py
src/boolean_model/migrations/__init__.py
src/boolean_model/migrations/__pycache__/0001_initial.cpython-35.pyc
src/boolean_model/migrations/__pycache__/__init__.cpython-35.pyc
src/fileTree/__init__.py
src/fileTree/admin.py
src/fileTree/apps.py
src/fileTree/forms.py
src/fileTree/models.py
src/fileTree/tests.py
src/fileTree/urls.py
src/fileTree/views.py
src/fileTree/__pycache__/__init__.cpython-35.pyc
src/fileTree/__pycache__/admin.cpython-35.pyc
src/fileTree/__pycache__/apps.cpython-35.pyc
