Metadata-Version: 1.0
Name: rxncon-workbench
Version: 0.99
Summary: A browser based interface for the rxncon framework.
Home-page: https://www.rxncon.org/
Author: Mathias Wajnberg
Author-email: mathiasw224@yahoo.de
License: LGPL License
Keywords: sysbio,signalling,systems biology
Platform: UNKNOWN
